Metadata-Version: 2.1
Name: pylogtail
Version: 0.9.1
Summary: Process log file lines that have not been read.
Home-page: https://gitlab.com/ixydo/python-logtail
Author: Jinn Koriech
Author-email: python-logtail@mx.ixydo.com
License: UNKNOWN
Platform: UNKNOWN
Classifier: Programming Language :: Python :: 3
Classifier: Development Status :: 4 - Beta
Classifier: License :: OSI Approved :: Mozilla Public License 2.0 (MPL 2.0)
Classifier: Operating System :: OS Independent
Requires-Python: >=3.7
